wordlist/__init__.py
wordlist_dp-0.1.dist-info/METADATA
wordlist_dp-0.1.dist-info/WHEEL
wordlist_dp-0.1.dist-info/top_level.txt
wordlist_dp-0.1.dist-info/RECORD
