Metadata-Version: 2.1
Name: wordlist-dp
Version: 0.1
Summary: A list of words
Home-page: https://github.com/Deepak-porwal04/wordlist
Author: Deepak Porwal
Author-email: dporwal04@gmail.com
License: UNKNOWN
Platform: UNKNOWN
